{
    "mutedRole": "926141246483873832",
    "lockMuted": [
        "926138143663607808"
    ],
    "channelModerationLogs": "926141703411335198",
    "staffUpdater": {
        "headstaff": [
            "926139854599888917"
        ],
        "staff": [
            "926139885339934760"
        ]
    },
    "automaticSanctions": {
        "maxWarnings": "3",
        "noLinks": {
            "enable": true,
            "allowedLinks": []
        },
        "spamTagWave": {
            "enable": true
        },
        "ghostTags": {
            "enable": true
        }
    }
}
